nastya_tail/__init__.py
nastya_tail/cli.py
nastya_tail_lnu-0.1.2.dist-info/METADATA
nastya_tail_lnu-0.1.2.dist-info/WHEEL
nastya_tail_lnu-0.1.2.dist-info/entry_points.txt
nastya_tail_lnu-0.1.2.dist-info/top_level.txt
nastya_tail_lnu-0.1.2.dist-info/RECORD
